tldx/__init__.py
tldx/cli.py
tldx/core.py
tldx-1.0.1.dist-info/METADATA
tldx-1.0.1.dist-info/WHEEL
tldx-1.0.1.dist-info/entry_points.txt
tldx-1.0.1.dist-info/top_level.txt
tldx-1.0.1.dist-info/RECORD
