Metadata-Version: 2.2
Name: tldx
Version: 1.0.1
Summary: TLD Expansion Tool for Bug Bounty Reconnaissance
Home-page: https://github.com/LocaMartin/tldx
Author: Loca Martin
Author-email: locaboyff@gmail.com
Keywords: bugbounty recon tld security
Classifier: Programming Language :: Python :: 3
Classifier: License :: OSI Approved :: MIT License
Classifier: Operating System :: OS Independent
Classifier: Topic :: Security
Classifier: Intended Audience :: Information Technology
Requires-Python: >=3.6
Requires-Dist: requests>=2.25.1
Requires-Dist: argparse>=1.4.0
Dynamic: author
Dynamic: author-email
Dynamic: classifier
Dynamic: description
Dynamic: description-content-type
Dynamic: home-page
Dynamic: keywords
Dynamic: requires-dist
Dynamic: requires-python
Dynamic: summary
